civicjson/__init__.py
civicjson/civicjson.py
civicjson/commands.py
civicjson/version.py
civicjson-0.1.1.dist-info/DESCRIPTION.rst
civicjson-0.1.1.dist-info/entry_points.txt
civicjson-0.1.1.dist-info/METADATA
civicjson-0.1.1.dist-info/metadata.json
civicjson-0.1.1.dist-info/RECORD
civicjson-0.1.1.dist-info/top_level.txt
civicjson-0.1.1.dist-info/WHEEL
tests/__init__.py
tests/base.py
tests/test.py
tests/test_version.py
