Metadata-Version: 2.0
Name: civicjson
Version: 0.1.1
Summary: Tools to make the civic.json (extended) specification easy to use.
Home-page: https://github.com/DCgov/civic.json-cli
Author: Emanuel Feld
Author-email: elefbet@gmail.com
License: CC0-1.0
Keywords: civic.json civic
Platform: UNKNOWN
Classifier: Development Status :: 3 - Alpha
Classifier: Intended Audience :: Developers
Classifier: License :: CC0 1.0 Universal (CC0 1.0) Public Domain Dedication
Classifier: Environment :: Console
Classifier: Programming Language :: Python :: 2.7
Classifier: Programming Language :: Python :: 3.3
Classifier: Programming Language :: Python :: 3.4
Classifier: Programming Language :: Python :: 3.5
Classifier: Operating System :: OS Independent
Requires-Dist: jsonschema (>=2.5.1)
Requires-Dist: requests (>=2.9.1)
